{
  "version": "6",
  "dialect": "sqlite",
  "id": "4ed832f5-bbad-48f5-981e-c48da429125f",
  "prevId": "9e12c942-12a3-4d94-a18b-a7fed2066e1c",
  "tables": {
    "conversations": {
      "name": "conversations",
      "columns": {
        "id": {
          "name": "id",
          "type": "text",
          "primaryKey": true,
          "notNull": true,
          "autoincrement": false
        },
        "kind": {
          "name": "kind",
          "type": "text",
          "primaryKey": false,
          "notNull": true,
          "autoincrement": false
        },
        "dm_key": {
          "name": "dm_key",
          "type": "text",
          "primaryKey": false,
          "notNull": false,
          "autoincrement": false
        },
        "created_at": {
          "name": "created_at",
          "type": "integer",
          "primaryKey": false,
          "notNull": true,
          "autoincrement": false
        }
      },
      "indexes": {
        "conversations_dm_key_unique": {
          "name": "conversations_dm_key_unique",
          "columns": [
            "dm_key"
          ],
          "isUnique": true
        }
      },
      "foreignKeys": {},
      "compositePrimaryKeys": {},
      "uniqueConstraints": {},
      "checkConstraints": {}
    },
    "users": {
      "name": "users",
      "columns": {
        "id": {
          "name": "id",
          "type": "text",
          "primaryKey": true,
          "notNull": true,
          "autoincrement": false
        },
        "email": {
          "name": "email",
          "type": "text",
          "primaryKey": false,
          "notNull": true,
          "autoincrement": false
        },
        "password_hash": {
          "name": "password_hash",
          "type": "text",
          "primaryKey": false,
          "notNull": false,
          "autoincrement": false
        },
        "auth_method": {
          "name": "auth_method",
          "type": "text",
          "primaryKey": false,
          "notNull": true,
          "autoincrement": false
        },
        "verification_token": {
          "name": "verification_token",
          "type": "text",
          "primaryKey": false,
          "notNull": false,
          "autoincrement": false
        },
        "verification_token_expire": {
          "name": "verification_token_expire",
          "type": "integer",
          "primaryKey": false,
          "notNull": false,
          "autoincrement": false
        },
        "isVerified": {
          "name": "isVerified",
          "type": "integer",
          "primaryKey": false,
          "notNull": true,
          "autoincrement": false,
          "default": false
        },
        "created_at": {
          "name": "created_at",
          "type": "integer",
          "primaryKey": false,
          "notNull": true,
          "autoincrement": false
        }
      },
      "indexes": {
        "users_email_unique": {
          "name": "users_email_unique",
          "columns": [
            "email"
          ],
          "isUnique": true
        }
      },
      "foreignKeys": {},
      "compositePrimaryKeys": {},
      "uniqueConstraints": {},
      "checkConstraints": {}
    }
  },
  "views": {},
  "enums": {},
  "_meta": {
    "schemas": {},
    "tables": {},
    "columns": {}
  },
  "internal": {
    "indexes": {}
  }
}